{"transactions":[{"payment_status":"paid","ride_id":"1762375908-8483","amount":54,"driver_id":"HU1M16DU","transaction_id":"1762375968-9504","ts":1762375968,"user_id":"K14C6R8X"},{"payment_status":"paid","ride_id":"1762376430-2045","amount":72,"driver_id":"HU1M16DU","transaction_id":"1762376525-5869","ts":1762376525,"user_id":"K14C6R8X"}],"ratings":[],"users":{"K14C6R8X":{"name":"Kalachand Mia","user_id":"K14C6R8X"}},"drivers":{"HU1M16DU":{"job":"taxi","availability_status":"off","vehicle_id":"TAXI8530","name":"Montu Mia","driver_id":"HU1M16DU","location":{"z":113.006591796875,"x":251.61758422851566,"y":395.0637512207031},"lastOff":1762450482,"lastOn":1762376434},"K14C6R8X":{"availability_status":"off","name":"Kalachand Mia","driver_id":"K14C6R8X","location":{"z":99.7626953125,"x":1657.2923583984376,"y":-2092.03515625},"lastOff":1762376598,"job":"unemployed"}},"rides":{"1762372386-3338":{"driver_id":"HU1M16DU","status":"completed","user_id":"K14C6R8X","pickup_location":{"z":30.95,"x":-189.59,"y":-1396.82},"end_time":1762372455,"start_time":1762372418,"ride_id":"1762372386-3338","note":"","fare_amount":29},"1762371808-1315":{"pickup_location":{"z":31.07,"x":-191.68,"y":-1398.55},"ride_id":"1762371808-1315","start_time":1762371812,"driver_id":"HU1M16DU","status":"in-progress","note":"","user_id":"K14C6R8X"},"1762372349-8160":{"pickup_location":{"z":30.95,"x":-189.59,"y":-1396.82},"ride_id":"1762372349-8160","driver_id":"HU1M16DU","status":"accepted","note":"","user_id":"K14C6R8X"},"1762369226-5633":{"pickup_location":{"z":29.34,"x":332.44,"y":-721.51},"ride_id":"1762369226-5633","start_time":1762369233,"driver_id":"HU1M16DU","status":"in-progress","note":"","user_id":"K14C6R8X"},"1762376430-2045":{"driver_id":"HU1M16DU","status":"completed","user_id":"K14C6R8X","pickup_location":{"z":29.35,"x":55.19,"y":-1662.65},"end_time":1762376525,"start_time":1762376477,"ride_id":"1762376430-2045","note":"","fare_amount":72},"1762369752-6662":{"pickup_location":{"z":29.27,"x":325.68,"y":-714.05},"ride_id":"1762369752-6662","start_time":1762369758,"driver_id":"HU1M16DU","status":"in-progress","note":"","user_id":"K14C6R8X"},"1762370359-2351":{"pickup_location":{"z":25.24,"x":503.58,"y":-869.49},"ride_id":"1762370359-2351","status":"booked","note":"","user_id":"K14C6R8X"},"1762369152-4619":{"pickup_location":{"z":29.34,"x":332.43,"y":-721.53},"ride_id":"1762369152-4619","start_time":1762369171,"driver_id":"HU1M16DU","status":"in-progress","note":"","user_id":"K14C6R8X"},"1762370635-7490":{"driver_id":"HU1M16DU","status":"completed","user_id":"K14C6R8X","pickup_location":{"z":25.91,"x":503.09,"y":-902.86},"end_time":1762370717,"start_time":1762370649,"ride_id":"1762370635-7490","note":"","fare_amount":79},"1762370368-8572":{"pickup_location":{"z":25.24,"x":503.58,"y":-869.49},"ride_id":"1762370368-8572","start_time":1762370407,"driver_id":"HU1M16DU","status":"in-progress","note":"","user_id":"K14C6R8X"},"1762371570-9247":{"pickup_location":{"z":30.93,"x":-190.92,"y":-1395.3},"ride_id":"1762371570-9247","driver_id":"HU1M16DU","status":"accepted","note":"","user_id":"K14C6R8X"},"1762371546-1883":{"pickup_location":{"z":30.93,"x":-190.92,"y":-1395.3},"ride_id":"1762371546-1883","status":"booked","note":"","user_id":"K14C6R8X"},"1762370302-9626":{"pickup_location":{"z":29.35,"x":328.76,"y":-719.42},"ride_id":"1762370302-9626","start_time":1762370315,"driver_id":"HU1M16DU","status":"in-progress","note":"","user_id":"K14C6R8X"},"1762375908-8483":{"driver_id":"HU1M16DU","status":"completed","user_id":"K14C6R8X","pickup_location":{"z":28.99,"x":153.96,"y":-1295.82},"end_time":1762375968,"start_time":1762375922,"ride_id":"1762375908-8483","note":"","fare_amount":54}},"vehicles":{"TAXI9119":{"license_plate":"TAXI9119","vehicle_id":"TAXI9119","model":"nightblade","driver_id":"HU1M16DU","vehicle_type":"sedan"},"TAXI1469":{"license_plate":"TAXI1469","vehicle_id":"TAXI1469","model":"nightblade","driver_id":"HU1M16DU","vehicle_type":"sedan"},"TAXI5491":{"license_plate":"TAXI5491","vehicle_id":"TAXI5491","model":"nightblade","driver_id":"HU1M16DU","vehicle_type":"sedan"},"TAXI8247":{"license_plate":"TAXI8247","vehicle_id":"TAXI8247","model":"nightblade","driver_id":"HU1M16DU","vehicle_type":"sedan"},"TAXI8530":{"license_plate":"TAXI8530","vehicle_id":"TAXI8530","model":"nightblade","driver_id":"HU1M16DU","vehicle_type":"sedan"},"TAXI7124":{"license_plate":"TAXI7124","vehicle_id":"TAXI7124","model":"nightblade","driver_id":"HU1M16DU","vehicle_type":"sedan"}}}